qsubr/__init__.py
qsubr/__main__.py
qsubr/qsubr.py
qsubr/data/environs.json
qsubr-0.3.dist-info/METADATA
qsubr-0.3.dist-info/WHEEL
qsubr-0.3.dist-info/entry_points.txt
qsubr-0.3.dist-info/top_level.txt
qsubr-0.3.dist-info/RECORD
