Metadata-Version: 2.1
Name: qsubr
Version: 0.3
Summary: A python wrapper for a quick qsub command
Home-page: https://github.com/scfurl/qsubr.git
Author: Scott Furlan
Author-email: scottfurlan@gmail.com
License: UNKNOWN
Platform: UNKNOWN
Classifier: Programming Language :: Python :: 3
Classifier: License :: OSI Approved :: MIT License
Classifier: Operating System :: OS Independent
Requires-Python: >=2.5
